odoo9_addon_stock_valued_picking_report-9.0.1.0.1-py2.7-nspkg.pth
odoo9_addon_stock_valued_picking_report-9.0.1.0.1.dist-info/DESCRIPTION.rst
odoo9_addon_stock_valued_picking_report-9.0.1.0.1.dist-info/METADATA
odoo9_addon_stock_valued_picking_report-9.0.1.0.1.dist-info/RECORD
odoo9_addon_stock_valued_picking_report-9.0.1.0.1.dist-info/WHEEL
odoo9_addon_stock_valued_picking_report-9.0.1.0.1.dist-info/metadata.json
odoo9_addon_stock_valued_picking_report-9.0.1.0.1.dist-info/namespace_packages.txt
odoo9_addon_stock_valued_picking_report-9.0.1.0.1.dist-info/top_level.txt
odoo_addons/stock_valued_picking_report/README.rst
odoo_addons/stock_valued_picking_report/__init__.py
odoo_addons/stock_valued_picking_report/__openerp__.py
odoo_addons/stock_valued_picking_report/i18n/es.po
odoo_addons/stock_valued_picking_report/models/__init__.py
odoo_addons/stock_valued_picking_report/models/res_partner.py
odoo_addons/stock_valued_picking_report/models/stock_pack_operation.py
odoo_addons/stock_valued_picking_report/models/stock_picking.py
odoo_addons/stock_valued_picking_report/report/stock_picking_valued_report.xml
odoo_addons/stock_valued_picking_report/security/ir.model.access.csv
odoo_addons/stock_valued_picking_report/tests/__init__.py
odoo_addons/stock_valued_picking_report/tests/test_stock_picking_valued.py
odoo_addons/stock_valued_picking_report/views/res_partner_view.xml
